MANIFEST.in
README.md
setup.cfg
setup.py
examples/__init__.py
examples/tabular_example.py
kaishi/__init__.py
kaishi.egg-info/PKG-INFO
kaishi.egg-info/SOURCES.txt
kaishi.egg-info/dependency_links.txt
kaishi.egg-info/not-zip-safe
kaishi.egg-info/requires.txt
kaishi.egg-info/top_level.txt
kaishi/core/__init__.py
kaishi/core/dataset.py
kaishi/core/file.py
kaishi/core/file_group.py
kaishi/core/labels.py
kaishi/core/misc.py
kaishi/core/pipeline.py
kaishi/core/pipeline_component.py
kaishi/core/printing.py
kaishi/core/filters/__init__.py
kaishi/core/filters/by_label.py
kaishi/core/filters/by_regex.py
kaishi/core/filters/duplicate_files.py
kaishi/core/filters/subsample.py
kaishi/core/labelers/__init__.py
kaishi/core/labelers/validation_and_test.py
kaishi/image/__init__.py
kaishi/image/dataset.py
kaishi/image/file.py
kaishi/image/file_group.py
kaishi/image/generator.py
kaishi/image/model.py
kaishi/image/ops.py
kaishi/image/util.py
kaishi/image/filters/__init__.py
kaishi/image/filters/invalid_file_extensions.py
kaishi/image/filters/invalid_image_headers.py
kaishi/image/filters/similar.py
kaishi/image/labelers/__init__.py
kaishi/image/labelers/generic_convnet.py
kaishi/image/transforms/__init__.py
kaishi/image/transforms/fix_rotation.py
kaishi/image/transforms/limit_dimensions.py
kaishi/image/transforms/to_grayscale.py
kaishi/tabular/__init__.py
kaishi/tabular/dataset.py
kaishi/tabular/file.py
kaishi/tabular/file_group.py
kaishi/tabular/aggregators/__init__.py
kaishi/tabular/aggregators/concatenate_dataframes.py
kaishi/tabular/filters/__init__.py
kaishi/tabular/filters/duplicate_rows_after_concatenation.py
kaishi/tabular/filters/duplicate_rows_each_dataframe.py
kaishi/tabular/filters/invalid_file_extensions.py
kaishi/weights/image_macro_issues_resnet18.pth